pickax/__init__.py
pickax-2021.6.0.dist-info/LICENSE
pickax-2021.6.0.dist-info/WHEEL
pickax-2021.6.0.dist-info/METADATA
pickax-2021.6.0.dist-info/RECORD
