Metadata-Version: 2.1
Name: pickax
Version: 2021.6.0
Summary: A library for creating neural networks in python based on jax
License: MIT
Author: Matt LeMay
Author-email: mplemay@users.noreply.github.com
Requires-Python: >=3.8,<4.0
Classifier: License :: OSI Approved :: MIT License
Classifier: Programming Language :: Python :: 3
Classifier: Programming Language :: Python :: 3.8
Classifier: Programming Language :: Python :: 3.9
Requires-Dist: jax (>=0.2.14,<0.3.0)
Requires-Dist: jaxlib (>=0.1.67,<0.2.0)
